eoml/__init__.py
eoml/automation/__init__.py
eoml/automation/configuration.py
eoml/automation/dag.py
eoml/automation/experience.py
eoml/automation/tasks.py
eoml/bin/__init__.py
eoml/bin/clean_checkpoint.py
eoml/bin/land_cover_mapping_toml.py
eoml/bin/mosaic_images.py
eoml/data/__init__.py
eoml/data/basic_geo_data.py
eoml/data/dataset_utils.py
eoml/data/persistence/__init__.py
eoml/data/persistence/generic.py
eoml/data/persistence/lmdb.py
eoml/data/persistence/serializer.py
eoml/raster/__init__.py
eoml/raster/band.py
eoml/raster/raster_reader.py
eoml/raster/raster_utils.py
eoml/raster/dataset/__init__.py
eoml/raster/dataset/extractor.py
eoml/torch/__init__.py
eoml/torch/model_low_use.py
eoml/torch/models.py
eoml/torch/resnet.py
eoml/torch/sample_statistic.py
eoml/torch/trainer.py
eoml/torch/trainer_v2.py
eoml/torch/cnn/__init__.py
eoml/torch/cnn/augmentation.py
eoml/torch/cnn/dataset_evaluator.py
eoml/torch/cnn/db_dataset.py
eoml/torch/cnn/map_dataset.py
eoml/torch/cnn/map_dataset_const_mem.py
eoml/torch/cnn/outputs_transformer.py
eoml/torch/cnn/torch_utils.py
eoml/torch/cnn/training_dataset.py
eoml/torch/cnn/windows_dataset.py
eoml/torch/dataset/__init__.py
eoml/torch/dataset/shade_dataset_tester.py
eoml/torch/dataset/shade_tree_dataset_creators.py
eoml-0.9.1.dist-info/METADATA
eoml-0.9.1.dist-info/WHEEL
eoml-0.9.1.dist-info/entry_points.txt
eoml-0.9.1.dist-info/RECORD
