Metadata-Version: 2.4
Name: eoml
Version: 0.9.1
Summary: library to manage GIS operation
Project-URL: Homepage, https://ciatgit.ciat.cgiar.org/Data_driven_sustainability_public/terra-i/eoml#
Project-URL: Documentation, https://ciatgit.ciat.cgiar.org/Data_driven_sustainability_public/terra-i/eoml#
Project-URL: Repository, https://ciatgit.ciat.cgiar.org/Data_driven_sustainability_public/terra-i/eoml#
Project-URL: Bug Tracker, https://ciatgit.ciat.cgiar.org/Data_driven_sustainability_public/terra-i/eoml/-/issues
Author-email: Thibaud Vantalon <t.vantalon@cgiar.org>
Maintainer-email: Thibaud Vantalon <t.vantalon@cgiar.org>
License: MIT License
Keywords: GIS,Rasterio
Classifier: Development Status :: 4 - Beta
Classifier: Programming Language :: Python
Requires-Python: >=3.12
Requires-Dist: fiona
Requires-Dist: geopandas
Requires-Dist: lmdb
Requires-Dist: msgpack
Requires-Dist: numpy
Requires-Dist: pydantic>=2.6
Requires-Dist: pyproj
Requires-Dist: rasterio
Requires-Dist: rasterop
Requires-Dist: rasterstats
Requires-Dist: scikit-learn
Requires-Dist: shapely
Requires-Dist: tensorboard
Requires-Dist: toml
Requires-Dist: tomli
Requires-Dist: torchmetrics
Requires-Dist: torchvision
Requires-Dist: tqdm
Requires-Dist: typer
